[{"name":"Illini Wushu","members":[{"id":"39","name":"Annie Chu"},{"id":"40","name":"Michael Ling"},{"id":"41","name":"Ian Meza"},{"id":"42","name":"Isabella White"},{"id":"43","name":"James Yang"},{"id":"44","name":"Olivia Yoshioka"}]},{"name":"Unlicensed Medical Care Professionals","members":[{"id":"46","name":"Michelle Chung"},{"id":"49","name":"Bryan Gao"},{"id":"53","name":"Dilan Kaza"},{"id":"54","name":"Carolyn Lee"},{"id":"59","name":"Jasmine Voon"},{"id":"63","name":"Joshua Zhu"}]},{"name":"Battered and Fried","members":[{"id":"48","name":"Kevin Fan"},{"id":"52","name":"Alex Jing"},{"id":"55","name":"William Ng"},{"id":"56","name":"Radhakund Ramnarine"},{"id":"57","name":"Kelvin Shi"},{"id":"61","name":"Angie Zhang"}]},{"name":"Who Let the Dawgs Out","members":[{"id":"101","name":"Ryan Le"},{"id":"102","name":"Miranda Li"},{"id":"105","name":"Fisher Ng"},{"id":"107","name":"Jasmine Tenison"},{"id":"110","name":"Heidi Wang"},{"id":"111","name":"Frank Wu"}]},{"name":"The UnBEARables","members":[{"id":"112","name":"Akshara Aditya"},{"id":"113","name":"David Cao"},{"id":"114","name":"Kaitlyn Chen"},{"id":"117","name":"Kaika Kusuma"},{"id":"123","name":"Queena Tran"},{"id":"124","name":"Angeline Yang"}]},{"name":"Bearly Conscious","members":[{"id":"116","name":"Michael Hughes"},{"id":"118","name":"Tiffany Le"},{"id":"119","name":"Nathan Lin"},{"id":"120","name":"Eshaan Mistry"},{"id":"122","name":"Ethan Shi"},{"id":"125","name":"Eric Zhu"}]},{"name":"[Groupset NAME]: \"null\"","members":[{"id":"141","name":"Hazelle Gunawan"},{"id":"149","name":"Sophia Li"},{"id":"150","name":"Joseph Liao"},{"id":"153","name":"Jessica Lin"},{"id":"157","name":"Peony Mong"},{"id":"173","name":"Adalia Zhou"}]},{"name":"Mushu Wushu","members":[{"id":"142","name":"Trevor Guo"},{"id":"159","name":"Alicia Sanoyca"},{"id":"164","name":"Ananya Visweswaran"},{"id":"166","name":"Isabelle Wang"},{"id":"168","name":"Sydney Woo"},{"id":"172","name":"Sarah Zhang"}]},{"name":"Mickey Mouse Trap House","members":[{"id":"152","name":"Ian Lim"},{"id":"158","name":"Ashley Oshiba"},{"id":"160","name":"Natalie Sun"},{"id":"161","name":"Talia Tam"},{"id":"165","name":"William Vo"},{"id":"170","name":"Brian Ye"}]},{"name":"Silk Issue","members":[{"id":"182","name":"Yao Bi"},{"id":"191","name":"Lauren Liu"},{"id":"193","name":"Connor Loewy"},{"id":"194","name":"Keerit Nijjar"},{"id":"195","name":"Austin Soohoo"},{"id":"198","name":"James Young"}]},{"name":"Pangea Panda Warriors","members":[{"id":"184","name":"Tara Chand"},{"id":"185","name":"Maya Chang"},{"id":"188","name":"Jerwey Guo"},{"id":"189","name":"Jessica Ju"},{"id":"190","name":"Jeremy Lei"},{"id":"199","name":"Zhoujie Yu"}]}]